slurmgen/__init__.py
slurmgen/gen.py
slurmgen/run.py
slurmgen/script.py
slurmgen/version.txt
slurmgen-3.14.0.dist-info/LICENSE.txt
slurmgen-3.14.0.dist-info/METADATA
slurmgen-3.14.0.dist-info/WHEEL
slurmgen-3.14.0.dist-info/entry_points.txt
slurmgen-3.14.0.dist-info/top_level.txt
slurmgen-3.14.0.dist-info/RECORD
