Metadata-Version: 2.1
Name: slurmgen
Version: 3.14.0
Summary: SlurmGen - Simple Manager for Slurm Jobs
Author-email: Thomas Guillod <guillod@otvam.ch>
Maintainer-email: Thomas Guillod <guillod@otvam.ch>
License: BSD-2-Clause
Project-URL: Homepage, https://github.com/otvam/slurmgen
Project-URL: Repository, https://github.com/otvam/slurmgen
Project-URL: Releases, https://github.com/otvam/slurmgen/releases
Project-URL: Issues, https://github.com/otvam/slurmgen/issues
Project-URL: Tags, https://github.com/otvam/slurmgen/tags
Keywords: Python,Slurm,HPC,Cluster
Classifier: Development Status :: 5 - Production/Stable
Classifier: License :: OSI Approved :: BSD License
Classifier: Intended Audience :: Science/Research
Classifier: Operating System :: OS Independent
Classifier: Programming Language :: Python :: 3
Classifier: Topic :: Scientific/Engineering
Classifier: Natural Language :: English
Classifier: Environment :: Console
Requires-Python: >=3.9
License-File: LICENSE.txt
Provides-Extra: dev
Requires-Dist: pip>=24.3; extra == "dev"
Requires-Dist: build>=1.2; extra == "dev"
Provides-Extra: test
Requires-Dist: ruff>=0.8; extra == "test"
